Metadata-Version: 1.1
Name: django-stored-messages
Version: 1.4.0
Summary: Django contrib.messages on steroids
Home-page: https://github.com/evonove/django-stored-messages
Author: evonove
Author-email: info@evonove.it
License: BSD
Keywords: django-stored-messages
Platform: UNKNOWN
Classifier: Development Status :: 5 - Production/Stable
Classifier: Framework :: Django
Classifier: Framework :: Django :: 1.8
Classifier: Framework :: Django :: 1.9
Classifier: Intended Audience :: Developers
Classifier: License :: OSI Approved :: BSD License
Classifier: Natural Language :: English
Classifier: Programming Language :: Python :: 2
Classifier: Programming Language :: Python :: 2.7
Classifier: Programming Language :: Python :: 3
Classifier: Programming Language :: Python :: 3.4
Classifier: Programming Language :: Python :: 3.5
